TakeSentimentAnalysis/__init__.py
TakeSentimentAnalysis/constants.py
TakeSentimentAnalysis/data.py
TakeSentimentAnalysis/mlflowlogger.py
TakeSentimentAnalysis/model.py
TakeSentimentAnalysis/train_transformers.py
TakeSentimentAnalysis/utils.py
TakeSentimentAnalysis/vocab.py
TakeSentimentAnalysis/predict/__init__.py
TakeSentimentAnalysis/predict/predict.py
TakeSentimentAnalysis/train/LSTMTrainer.py
TakeSentimentAnalysis/train/__init__.py
TakeBlipSentimentAnalysis-0.0.1b0.dist-info/METADATA
TakeBlipSentimentAnalysis-0.0.1b0.dist-info/WHEEL
TakeBlipSentimentAnalysis-0.0.1b0.dist-info/top_level.txt
TakeBlipSentimentAnalysis-0.0.1b0.dist-info/RECORD
