Metadata-Version: 2.1
Name: TakeBlipSentimentAnalysis
Version: 0.0.1b0
Summary: Sentiment Analysis Package
Home-page: UNKNOWN
Author: Data and Analytics Research
Author-email: analytics.dar@take.net
License: UNKNOWN
Keywords: sentiment analysis
Platform: UNKNOWN
Classifier: Programming Language :: Python :: 3
Classifier: License :: OSI Approved :: MIT License
Classifier: Operating System :: OS Independent
Requires-Dist: gensim (==3.8.3)
Requires-Dist: take-text-preprocess (==0.0.5)
Requires-Dist: torch (==1.9.0)
Requires-Dist: numpy (==1.19.1)
